spdcalc_py-1.0.1.dist-info/METADATA
spdcalc_py-1.0.1.dist-info/WHEEL
spdcalc_py-1.0.1.dist-info/licenses/LICENSE
spdcalc/__init__.py
spdcalc/spdcalc.cpython-312-darwin.so
spdcalc_py-1.0.1.dist-info/RECORD
